{
    "useSession": "false",
    "showPageSizeSelector": "true",
    "rowActions": [],
    "columns": [
        {
            "name": "invoice_number",
            "id": "column_0",
            "label": "Invoice Number"
        },
        {
            "name": "currency",
            "format": {
                "className": "org.joget.plugin.enterprise.OptionsValueFormatter",
                "properties": {
                    "optionsBinder": {
                        "className": "",
                        "properties": {}
                    },
                    "options": [
                        {
                            "label": "INR",
                            "value": "INR",
                            "grouping": ""
                        },
                        {
                            "label": "USD",
                            "value": "USD",
                            "grouping": ""
                        },
                        {
                            "label": "EUR",
                            "value": "EUR",
                            "grouping": ""
                        }
                    ]
                }
            },
            "id": "column_1",
            "label": "Currency"
        },
        {
            "name": "total_amount",
            "id": "column_2",
            "label": "Total Amount"
        }
    ],
    "pageSize": 0,
    "orderBy": "",
    "filters": [],
    "pageSizeSelectorOptions": "10,20,30,40,50,100",
    "buttonPosition": "bothLeft",
    "checkboxPosition": "left",
    "name": "List - Game Payment",
    "id": "list_gamePayment",
    "binder": {
        "className": "org.joget.plugin.enterprise.AdvancedFormRowDataListBinder",
        "properties": {"formDefId": "gamePayment"}
    },
    "actions": [],
    "order": ""
}